dash_google_picker/Documents.py
dash_google_picker/Enums.py
dash_google_picker/GooglePicker.py
dash_google_picker/Views.py
dash_google_picker/__init__.py
dash_google_picker/_imports_.py
dash_google_picker/dash_google_picker.min.js
dash_google_picker/dash_google_picker.min.js.map
dash_google_picker/metadata.json
dash_google_picker/package-info.json
dash_google_picker-1.1.0.dist-info/LICENSE
dash_google_picker-1.1.0.dist-info/METADATA
dash_google_picker-1.1.0.dist-info/WHEEL
dash_google_picker-1.1.0.dist-info/top_level.txt
dash_google_picker-1.1.0.dist-info/RECORD
