Metadata-Version: 2.1
Name: dash-google-picker
Version: 1.1.0
Summary: Google picker component for dash
Author: lpawlick
License: MIT
Project-URL: Documentation, https://docs.pawlick.dev/projects/dash_google_picker
Project-URL: Source, https://github.com/lpawlick/dash_google_picker
Project-URL: Tracker, https://github.com/lpawlick/dash_google_picker/issues
Keywords: dash google file picker
Classifier: Framework :: Dash
Classifier: Programming Language :: Python :: 3.6
Classifier: Programming Language :: Python :: 3.7
Classifier: Programming Language :: Python :: 3.8
Classifier: Programming Language :: Python :: 3.9
Classifier: Programming Language :: Python :: 3.10
Classifier: Programming Language :: Python :: 3.11
Classifier: Development Status :: 5 - Production/Stable
Requires-Python: >=3.6
License-File: LICENSE
Requires-Dist: dash
